{
	"name": "CommonsMetadata",
	"author": "Brian Wolff",
	"url": "https://www.mediawiki.org/wiki/Extension:CommonsMetadata",
	"descriptionmsg": "commonsmetadata-desc",
	"license-name": "GPL-2.0-or-later",
	"type": "other",
	"requires": {
		"MediaWiki": ">= 1.31.0"
	},
	"Hooks": {
		"GetExtendedMetadata": [
			"CommonsMetadata\\HookHandler::onGetExtendedMetadata"
		],
		"ValidateExtendedMetadataCache": [
			"CommonsMetadata\\HookHandler::onValidateExtendedMetadataCache"
		],
		"ContentAlterParserOutput": [
			"CommonsMetadata\\HookHandler::onContentAlterParserOutput"
		]
	},
	"MessagesDirs": {
		"CommonsMetadata": [
			"i18n"
		]
	},
	"config": {
		"CommonsMetadataForceRecalculate": false,
		"CommonsMetadataSetTrackingCategories": false
	},
	"AutoloadNamespaces": {
		"CommonsMetadata\\": "src/"
	},
	"TrackingCategories": [
		"commonsmetadata-trackingcategory-no-license",
		"commonsmetadata-trackingcategory-no-description",
		"commonsmetadata-trackingcategory-no-author",
		"commonsmetadata-trackingcategory-no-source",
		"commonsmetadata-trackingcategory-no-patent"
	],
	"manifest_version": 1
}
